MANIFEST.in
setup.cfg
setup.py
config/escw.config
config/example.config
elasticsearchcloudwatch/__init__.py
elasticsearchcloudwatch/cloud_watch_client.py
elasticsearchcloudwatch.egg-info/PKG-INFO
elasticsearchcloudwatch.egg-info/SOURCES.txt
elasticsearchcloudwatch.egg-info/dependency_links.txt
elasticsearchcloudwatch.egg-info/entry_points.txt
elasticsearchcloudwatch.egg-info/requires.txt
elasticsearchcloudwatch.egg-info/top_level.txt
elasticsearchcloudwatch.egg-info/zip-safe
elasticsearchcloudwatch/cli/__init__.py
elasticsearchcloudwatch/cli/get_web_request.py
elasticsearchcloudwatch/cli/put_web_request.py