Metadata-Version: 1.1
Name: elasticsearchcloudwatch
Version: 0.1.8
Summary: Elasticsearch monitoring scripts for CloudWatch
Home-page: https://rubelw@bitbucket.org/rubelw/elasticsearchcloudwatch.git
Author: Will Rubel
Author-email: willrubel@gmail.com
License: Apache License (2.0)
Keywords: elasticsearch monitoring cloudwatch amazon web services aws ec2
Platform: UNKNOWN
Classifier: License :: OSI Approved :: Apache Software License
Classifier: Topic :: System :: Monitoring
